spark_archetype_tools/__init__.py
spark_archetype_tools/functions/__init__.py
spark_archetype_tools/functions/generator.py
spark_archetype_tools/utils/__init__.py
spark_archetype_tools/utils/resource/__init__.py
spark_archetype_tools-0.0.1.dist-info/LICENSE
spark_archetype_tools-0.0.1.dist-info/METADATA
spark_archetype_tools-0.0.1.dist-info/WHEEL
spark_archetype_tools-0.0.1.dist-info/top_level.txt
spark_archetype_tools-0.0.1.dist-info/RECORD
