Metadata-Version: 2.1
Name: spark-archetype-tools
Version: 0.0.1
Summary: spark_archetype_tools
Home-page: https://github.com/jonaqp/spark_archetype_tools/
Author: Jonathan Quiza
Author-email: jony327@gmail.com
License: UNKNOWN
Download-URL: https://github.com/jonaqp/spark_archetype_tools/archive/main.zip
Keywords: spark,archetype,kirby,hammurabi,scala,scaffolder
Platform: UNKNOWN
Classifier: Development Status :: 5 - Production/Stable
Classifier: Intended Audience :: Developers
Classifier: Intended Audience :: Science/Research
Classifier: Topic :: Scientific/Engineering :: Artificial Intelligence
Classifier: License :: OSI Approved :: Apache Software License
Classifier: Programming Language :: Python :: 3.9
License-File: LICENSE
Requires-Dist: pyhocon
